unach_photo/__init__.py
unach_photo/admin.py
unach_photo/apps.py
unach_photo/models.py
unach_photo/tests.py
unach_photo/urls.py
unach_photo/views.py
unach_photo/migrations/0001_initial.py
unach_photo/migrations/__init__.py
unach_photo/static/css/unach_photo.css
unach_photo/static/js/unach_photo.js
unach_photo/templates/unach_photo/base.html
unach_photo/templates/unach_photo/test.html
unach_photo/templatetags/__init__.py
unach_photo/templatetags/unach_photo_extras.py
unach_photo-0.2.0.dist-info/DESCRIPTION.rst
unach_photo-0.2.0.dist-info/METADATA
unach_photo-0.2.0.dist-info/RECORD
unach_photo-0.2.0.dist-info/WHEEL
unach_photo-0.2.0.dist-info/metadata.json
unach_photo-0.2.0.dist-info/top_level.txt
