Metadata-Version: 2.0
Name: unach-photo
Version: 0.2.0
Summary: Aplicación Django cliente para conectar con repositorios de fotografías de personas relacionadas a la unach.
Home-page: https://github.com/javierhuerta/unach-photo
Author: Javier Huerta
Author-email: javierhuerta@unach.cl
License: MIT
Keywords: unach-photo
Platform: UNKNOWN
Classifier: Development Status :: 3 - Alpha
Classifier: Framework :: Django
Classifier: Framework :: Django :: 1.10
Classifier: Intended Audience :: Developers
Classifier: License :: OSI Approved :: BSD License
Classifier: Natural Language :: English
Classifier: Programming Language :: Python :: 2
Classifier: Programming Language :: Python :: 2.7
Classifier: Programming Language :: Python :: 3
Classifier: Programming Language :: Python :: 3.4
Classifier: Programming Language :: Python :: 3.5
